pplx_cli/__init__.py
pplx_cli/api.py
pplx_cli/chat_history.py
pplx_cli/cli.py
pplx_cli/config.py
pplx_cli/main.py
pplx_cli/migrations/__init__.py
pplx_cli/migrations/migrate_to_rag.py
pplx_cli/notes.py
pplx_cli/rag/__init__.py
pplx_cli/rag/database.py
pplx_cli/rag/embeddings.py
pplx_cli/rag/indexer.py
pplx_cli/rag/search.py
pplx_cli-0.2.6.dist-info/METADATA
pplx_cli-0.2.6.dist-info/WHEEL
pplx_cli-0.2.6.dist-info/entry_points.txt
pplx_cli-0.2.6.dist-info/licenses/LICENSE
pplx_cli-0.2.6.dist-info/RECORD
