Metadata-Version: 2.4
Name: pplx-cli
Version: 0.2.6
Summary: A command-line notes and RAG interface for Perplexity AI API
License-File: LICENSE
Keywords: perplexity,ai,cli,llm
Author: xerexcoded
Author-email: arnavbanerjee61@gmail.com
Requires-Python: >=3.12,<4.0
Classifier: Development Status :: 4 - Beta
Classifier: Environment :: Console
Classifier: Intended Audience :: Developers
Classifier: License :: OSI Approved :: MIT License
Classifier: Programming Language :: Python :: 3
Classifier: Programming Language :: Python :: 3.12
Classifier: Programming Language :: Python :: 3.13
Classifier: Programming Language :: Python :: 3.14
Classifier: Topic :: Software Development :: Libraries :: Python Modules
Requires-Dist: click (>=8.0.0,<8.2.0)
Requires-Dist: numpy (>=1.26.0,<2.0.0)
Requires-Dist: openpyxl (>=3.1.5,<4.0.0)
Requires-Dist: pandas (>=2.1.0,<3.0.0)
Requires-Dist: python-dotenv (>=1.0.1,<2.0.0)
Requires-Dist: requests (>=2.31.0,<3.0.0)
Requires-Dist: sentence-transformers (>=3.0.0,<4.0.0)
Requires-Dist: sqlite-utils (>=3.35,<3.38)
Requires-Dist: toml (>=0.10.2,<0.11.0)
Requires-Dist: torch (>=2.0.0,<3.0.0)
Requires-Dist: transformers (>=4.40.0,<5.0.0)
Requires-Dist: typer (>=0.15.0,<0.16.0)
Project-URL: Documentation, https://github.com/xerexcoded/pplx-cli#readme
Project-URL: Homepage, https://github.com/xerexcoded/pplx-cli
Project-URL: Repository, https://github.com/xerexcoded/pplx-cli
